[
  {
    "file": "sample_001.png",
    "label": "Suspicious",
    "x": 0.2143,
    "y": 0.3512,
    "w": 0.1820,
    "h": 0.0960,
    "x_pixel": 219,
    "y_pixel": 269,
    "w_pixel": 186,
    "h_pixel": 73,
    "image_width": 1024,
    "image_height": 768
  },
  {
    "file": "sample_001.png",
    "label": "Confirmed Cancer",
    "x": 0.5821,
    "y": 0.4103,
    "w": 0.0921,
    "h": 0.0643,
    "x_pixel": 596,
    "y_pixel": 315,
    "w_pixel": 94,
    "h_pixel": 49,
    "image_width": 1024,
    "image_height": 768
  }
]
